[
  { "bg": "bg_ch01_crimson" },
  { "bgm": "bgm_ch01" },
  { "chara": { "id": "akari", "expr": "normal", "pos": "center" } },
  { "text": { "name": "あかり", "body": "……旅人さん、正直に聞いていい？" } },
  { "text": { "name": "???", "body": "なんでも。" } },
  { "chara": { "id": "akari", "expr": "sad", "pos": "center" } },
  { "text": { "name": "あかり", "body": "私を解放して……外に連れ出してくれる？　本当に？" } },
  { "text": { "name": "???", "body": "ああ、約束する。" } },
  { "chara": { "id": "akari", "expr": "surprise", "pos": "center" } },
  { "text": { "name": "あかり", "body": "……っ！" } },
  { "chara": { "id": "akari", "expr": "smile", "pos": "center" } },
  { "text": { "name": "あかり", "body": "ありがとう。じゃあ今度こそ本気でいくよ。このステージ、今まで一番難しいから！" } },
  { "choice": [
    { "label": "燃えてきた！", "flag": "akari_friendly+1" },
    { "label": "慎重にいく", "flag": "akari_friendly+0" }
  ]},
  { "chara": { "id": "akari", "expr": "smile", "pos": "center" } },
  { "text": { "name": "あかり", "body": "その顔、好きだよ。さあ、行こう！" } }
]
