[
  {
    "bg": "stage2"
  },
  {
    "bgm": "bgm_chapter_clear"
  },
  {
    "text": {
      "name": "",
      "body": "氷が、溶けていく。"
    }
  },
  {
    "text": {
      "name": "",
      "body": "壁という壁を覆っていた青い氷が、表面から少しずつ、水滴になって滴り落ちる。"
    }
  },
  {
    "text": {
      "name": "",
      "body": "凍りついていた階層全体に、穏やかな『青』の光が満ちていく。嵐の後に見上げる、澄み切った空の色だった。"
    }
  },
  {
    "text": {
      "name": "",
      "body": "そして、その光の中で——みおが、初めて自分の腕をほどいた。両腕で抱きしめていた肩から、力が抜けて、垂れる。"
    }
  },
  {
    "chara": {
      "id": "mio",
      "expr": "sad",
      "pos": "center",
      "show": true
    }
  },
  {
    "text": {
      "name": "みお",
      "body": "……どうして。"
    }
  },
  {
    "text": {
      "name": "みお",
      "body": "このまま凍っていれば、何も感じなくて済んだのに。"
    }
  },
  {
    "text": {
      "name": "みお",
      "body": "痛みに耐えるだけでよかったのに……！"
    }
  },
  {
    "text": {
      "name": "",
      "body": "彼女の声は、初めて震えていた。氷の柱に閉じ込められていた声が、ようやく外に出る、その出方を覚えていないかのように。"
    }
  },
  {
    "text": {
      "name": "主人公",
      "body": "みお……"
    }
  },
  {
    "text": {
      "name": "みお",
      "body": "……私ね、あなたに怒っていたんじゃないの。"
    }
  },
  {
    "text": {
      "name": "みお",
      "body": "怖かったのよ。"
    }
  },
  {
    "text": {
      "name": "みお",
      "body": "また誰かを大切に思って、また失うことが。"
    }
  },
  {
    "text": {
      "name": "みお",
      "body": "だから……壁を作って、全部凍らせた。誰のことも好きにならないように。誰のことも、思い出さないように。"
    }
  },
  {
    "text": {
      "name": "主人公",
      "body": "それが……君の正体か。"
    }
  },
  {
    "text": {
      "name": "主人公",
      "body": "僕が心を守るために張った、防衛機制……？"
    }
  },
  {
    "chara": {
      "id": "mio",
      "expr": "sad",
      "pos": "center"
    }
  },
  {
    "text": {
      "name": "みお",
      "body": "あなたが傷つかないように、心が自動で動かした結果よ。"
    }
  },
  {
    "text": {
      "name": "みお",
      "body": "でも……ずっと泣いていた。凍った氷の中で、ずっと。"
    }
  },
  {
    "text": {
      "name": "みお",
      "body": "守るって、本当は——『何かを感じる権利』も、いっしょに凍らせてたってこと。"
    }
  },
  {
    "text": {
      "name": "主人公",
      "body": "……すまなかった。"
    }
  },
  {
    "text": {
      "name": "主人公",
      "body": "君がそんな場所に閉じ込められていたなんて、気づいてやれなかった。"
    }
  },
  {
    "text": {
      "name": "主人公",
      "body": "自分の中の感情を凍らせて生きるのは、確かに、楽だった。痛みも喜びも、なくなるから。でも、君がその檻の中で泣いていたなんて、考えもしなかった。"
    }
  },
  {
    "chara": {
      "id": "mio",
      "expr": "smile",
      "pos": "center"
    }
  },
  {
    "text": {
      "name": "みお",
      "body": "謝らないで。"
    }
  },
  {
    "text": {
      "name": "みお",
      "body": "あなたが来てくれたじゃない。"
    }
  },
  {
    "text": {
      "name": "みお",
      "body": "……少しだけ、溶けた気がするわ。ありがとう。"
    }
  },
  {
    "text": {
      "name": "",
      "body": "みおの輪郭が、青い光の粒子となって、ゆっくりとほどけていく。"
    }
  },
  {
    "text": {
      "name": "",
      "body": "氷の鏡に映っていた彼女の影も、いっしょに溶けて、水となって流れた。"
    }
  },
  {
    "chara": {
      "id": "mio",
      "expr": "smile",
      "pos": "center"
    }
  },
  {
    "text": {
      "name": "みお",
      "body": "……上に行って。"
    }
  },
  {
    "text": {
      "name": "みお",
      "body": "すずは優しすぎるから、気をつけて。甘えすぎたら、前に進めなくなるから。"
    }
  },
  {
    "text": {
      "name": "みお",
      "body": "あの子の優しさは、本物。だからこそ、危ない。"
    }
  },
  {
    "effect": {
      "type": "fade_out",
      "duration": 2000
    }
  },
  {
    "text": {
      "name": "主人公",
      "body": "（悲しみ……か）"
    }
  },
  {
    "text": {
      "name": "主人公",
      "body": "（ずっと感じないように凍らせていた、大切な感情。少しずつ、思い出してきている気がする）"
    }
  },
  {
    "text": {
      "name": "主人公",
      "body": "（凍らないままで、それでも生きていくのは、どれくらい辛いんだろう。あるいは、どれくらい、優しいんだろう）"
    }
  },
  {
    "effect": {
      "type": "fade_out",
      "duration": 1500
    }
  }
]
