[
  {
    "bg": "stage4"
  },
  {
    "bgm": "bgm_clockwork"
  },
  {
    "text": {
      "name": "",
      "body": "歯車の通路を進むと、空中に砂時計のような透明な装置が、いくつも浮かんでいるのが見えた。"
    }
  },
  {
    "text": {
      "name": "",
      "body": "中で揺らめく砂は金色で、ひっくり返るたびに、空気がふわっと甘くなる気がする。"
    }
  },
  {
    "chara": {
      "id": "himari",
      "expr": "normal",
      "pos": "center",
      "show": true
    }
  },
  {
    "text": {
      "name": "ひまり",
      "body": "ねえ、次は時間が絡んでくるやつだよ！　砂時計のタイルが混じってて、うまく使うと時間が増えるの！"
    }
  },
  {
    "text": {
      "name": "ひまり",
      "body": "もちろん、見逃したら時間ぐーんと減っちゃうから、要注意ね！"
    }
  },
  {
    "text": {
      "name": "主人公",
      "body": "時間が増える……？"
    }
  },
  {
    "text": {
      "name": "主人公",
      "body": "（妙だな。時間って、世界中の誰にとっても、一秒は一秒のはずなのに）"
    }
  },
  {
    "text": {
      "name": "主人公",
      "body": "それはまるで、新しいアイデアが生まれた時の感覚に似ているな。時間を忘れて夢中になる、あの感じ。"
    }
  },
  {
    "text": {
      "name": "主人公",
      "body": "気づいたら朝になっていて、でも疲れた気はしなくて、むしろ寝てない方が冴えている——あの、いまの時計より自分の脳の方が速い、って感じ。"
    }
  },
  {
    "chara": {
      "id": "himari",
      "expr": "smile",
      "pos": "center"
    }
  },
  {
    "text": {
      "name": "ひまり",
      "body": "わかる！　わかるよ！　あなた、やっぱりまだ生きてるじゃない！"
    }
  },
  {
    "text": {
      "name": "ひまり",
      "body": "それを『フロー』とか『ゾーン』とか言うらしいんだけどさ、私は『砂時計が逆さに飛んでる時間』って呼んでるの。だってそんな感じじゃない？"
    }
  },
  {
    "text": {
      "name": "主人公",
      "body": "（……命名が、抜群にいいな）"
    }
  },
  {
    "text": {
      "name": "ひまり",
      "body": "じゃ、いっくよー！　砂時計、ちゃんと拾ってね！"
    }
  }
]
