[
  {
    "bgm": "bgm_flashback"
  },
  {
    "bg": "bg_atelier_morning"
  },
  {
    "text": {
      "name": "",
      "body": "──これは、最後の記憶だ。"
    }
  },
  {
    "text": {
      "name": "",
      "body": "事故の前日。二人でアトリエにいた夜。"
    }
  },
  {
    "text": {
      "name": "",
      "body": "主人公は、ようやく完成に近づいた絵の前で、筆を止めていた。"
    }
  },
  {
    "text": {
      "name": "真白",
      "body": "……どうしたの。筆が止まってる"
    }
  },
  {
    "text": {
      "name": "主人公",
      "body": "……なんか怖くて"
    }
  },
  {
    "text": {
      "name": "真白",
      "body": "怖い？　なんで"
    }
  },
  {
    "text": {
      "name": "主人公",
      "body": "完成したら——それで終わりになる気がして"
    }
  },
  {
    "text": {
      "name": "真白",
      "body": "（笑って）馬鹿だな。"
    }
  },
  {
    "text": {
      "name": "真白",
      "body": "終わりになったらまた描けばいいじゃない"
    }
  },
  {
    "text": {
      "name": "主人公",
      "body": "……お前に、見せたいと思って描いてる"
    }
  },
  {
    "text": {
      "name": "真白",
      "body": "（少し黙って）……うん。知ってるよ"
    }
  },
  {
    "text": {
      "name": "真白",
      "body": "ねえ——約束して"
    }
  },
  {
    "text": {
      "name": "主人公",
      "body": "なんだ"
    }
  },
  {
    "text": {
      "name": "真白",
      "body": "私がいなくなっても、描き続けて。"
    }
  },
  {
    "text": {
      "name": "真白",
      "body": "あなたの色は、あなたのものだから。"
    }
  },
  {
    "text": {
      "name": "真白",
      "body": "誰かのためだけじゃなくて——あなた自身のために、描いてよ"
    }
  },
  {
    "text": {
      "name": "主人公",
      "body": "縁起でもないことを言うな"
    }
  },
  {
    "text": {
      "name": "真白",
      "body": "（微笑んで）……いいから、約束して"
    }
  },
  {
    "text": {
      "name": "主人公",
      "body": "……ああ。約束する"
    }
  },
  {
    "text": {
      "name": "",
      "body": "翌日、真白は事故に遭った。"
    }
  },
  {
    "text": {
      "name": "主人公",
      "body": "（……ごめん、真白。約束を守れてなかった）"
    }
  },
  {
    "text": {
      "name": "主人公",
      "body": "（でも——今度は、守る）"
    }
  },
  {
    "text": {
      "name": "主人公",
      "body": "（描くよ。何度でも——ずっと）"
    }
  }
]
